UnderstandingModelViewController/README.md
UnderstandingModelViewController/__init__.py
UnderstandingModelViewController/__main__.py
UnderstandingModelViewController/file.epub
UnderstandingModelViewController/index.html
UnderstandingModelViewController/css/__init__.py
UnderstandingModelViewController/css/annotations.css
UnderstandingModelViewController/css/main.css
UnderstandingModelViewController/css/normalize.css
UnderstandingModelViewController/css/popup.css
UnderstandingModelViewController/font/__init__.py
UnderstandingModelViewController/font/fontello.eot
UnderstandingModelViewController/font/fontello.svg
UnderstandingModelViewController/font/fontello.ttf
UnderstandingModelViewController/font/fontello.woff
UnderstandingModelViewController/img/__init__.py
UnderstandingModelViewController/img/annotator-glyph-sprite.png
UnderstandingModelViewController/img/annotator-icon-sprite.png
UnderstandingModelViewController/img/apple-touch-icon.png
UnderstandingModelViewController/img/cancelfullscreen.png
UnderstandingModelViewController/img/close.png
UnderstandingModelViewController/img/fullscreen.png
UnderstandingModelViewController/img/loader.gif
UnderstandingModelViewController/img/menu-icon.png
UnderstandingModelViewController/img/save.png
UnderstandingModelViewController/img/saved.png
UnderstandingModelViewController/img/settings-s.png
UnderstandingModelViewController/img/settings.png
UnderstandingModelViewController/img/star.png
UnderstandingModelViewController/js/__init__.py
UnderstandingModelViewController/js/epub.js
UnderstandingModelViewController/js/epub.min.js
UnderstandingModelViewController/js/epub.min.map
UnderstandingModelViewController/js/hooks.min.js
UnderstandingModelViewController/js/hooks.min.map
UnderstandingModelViewController/js/reader.js
UnderstandingModelViewController/js/reader.js.map
UnderstandingModelViewController/js/reader.min.js
UnderstandingModelViewController/js/reader.min.map
UnderstandingModelViewController/js/hooks/__init__.py
understanding_model_view_controller-2024.3.4.0.dist-info/METADATA
understanding_model_view_controller-2024.3.4.0.dist-info/WHEEL
understanding_model_view_controller-2024.3.4.0.dist-info/entry_points.txt
understanding_model_view_controller-2024.3.4.0.dist-info/top_level.txt
understanding_model_view_controller-2024.3.4.0.dist-info/RECORD
